pylovepdf_flavor/__init__.py
pylovepdf_flavor/file.py
pylovepdf_flavor/ilovepdf.py
pylovepdf_flavor/request.py
pylovepdf_flavor/response.py
pylovepdf_flavor/task.py
pylovepdf_flavor/tools/__init__.py
pylovepdf_flavor/tools/compress.py
pylovepdf_flavor/tools/imagepdf.py
pylovepdf_flavor/tools/merge.py
pylovepdf_flavor/tools/officepdf.py
pylovepdf_flavor/tools/pagenumber.py
pylovepdf_flavor/tools/pdfa.py
pylovepdf_flavor/tools/pdfjpg.py
pylovepdf_flavor/tools/protect.py
pylovepdf_flavor/tools/rotate.py
pylovepdf_flavor/tools/split.py
pylovepdf_flavor/tools/unlock.py
pylovepdf_flavor/tools/validatepdfa.py
pylovepdf_flavor/tools/watermark.py
pylovepdf_flavor-1.3.3.4.dist-info/LICENSE.txt
pylovepdf_flavor-1.3.3.4.dist-info/METADATA
pylovepdf_flavor-1.3.3.4.dist-info/WHEEL
pylovepdf_flavor-1.3.3.4.dist-info/top_level.txt
pylovepdf_flavor-1.3.3.4.dist-info/RECORD
