Metadata-Version: 2.1
Name: pylovepdf-flavor
Version: 1.3.3.4
Summary: ilovepdf.com python API library
Home-page: https://github.com/AndyBTuttofare/pylovepdfhvjv
Author: Andrea Bruschi
Author-email: moonx2006@gmail.com
License: GNU GPLv3
Keywords: pdf unlock compress manipulate edit protect pdftojpg jpgtopdf pdfa
Classifier: Development Status :: 5 - Production/Stable
Classifier: License :: OSI Approved :: GNU General Public License v3 (GPLv3)
Classifier: Programming Language :: Python :: 3.6
Classifier: Topic :: Software Development :: Libraries :: Python Modules
Requires-Python: >=3.7
License-File: LICENSE.txt
Requires-Dist: requests
Requires-Dist: urllib3
